practicaPyr/__init__.py
practicaPyr/practicaPyr.py
practicaPyr-0.1.dist-info/METADATA
practicaPyr-0.1.dist-info/WHEEL
practicaPyr-0.1.dist-info/license.txt
practicaPyr-0.1.dist-info/top_level.txt
practicaPyr-0.1.dist-info/RECORD
